simplerdap/__init__.py
simplerdap/core.py
simplerdap/exceptions.py
simplerdap-0.1.0.dist-info/licenses/LICENSE
simplerdap-0.1.0.dist-info/METADATA
simplerdap-0.1.0.dist-info/WHEEL
simplerdap-0.1.0.dist-info/top_level.txt
simplerdap-0.1.0.dist-info/RECORD
