Metadata-Version: 2.4
Name: simplerdap
Version: 0.1.0
Summary: A simple, lightweight Python library for RDAP lookups using IANA bootstrap data or custom bootstrap files.
Author-email: deepnor <hellnor@outlook.com>
License-Expression: MIT
Project-URL: Repository, https://github.com/deepnor/SimpleRDAP
Keywords: rdap,iana,lookup,domain,ip address,asn
Classifier: Development Status :: 3 - Alpha
Classifier: Intended Audience :: Developers
Classifier: Programming Language :: Python :: 3
Classifier: Programming Language :: Python :: 3.7
Classifier: Programming Language :: Python :: 3.8
Classifier: Programming Language :: Python :: 3.9
Classifier: Programming Language :: Python :: 3.10
Classifier: Programming Language :: Python :: 3.11
Classifier: Operating System :: OS Independent
Classifier: Topic :: Internet
Classifier: Topic :: Software Development :: Libraries :: Python Modules
Requires-Python: >=3.7
License-File: LICENSE
Dynamic: license-file
